socketapp/__init__.py
socketapp/client.py
socketapp/event.py
socketapp/server.py
socketapp-0.1.6.dist-info/LICENSE
socketapp-0.1.6.dist-info/METADATA
socketapp-0.1.6.dist-info/WHEEL
socketapp-0.1.6.dist-info/RECORD
