Metadata-Version: 2.1
Name: socketapp
Version: 0.1.6
Summary: An opinionated library for creating websocket-based applications.
License: Unlicense
Author: CircuitSacul
Author-email: circuitsacul@gmail.com
Requires-Python: >=3.8,<4.0
Classifier: License :: Other/Proprietary License
Classifier: Programming Language :: Python :: 3
Classifier: Programming Language :: Python :: 3.8
Classifier: Programming Language :: Python :: 3.9
Classifier: Programming Language :: Python :: 3.10
Classifier: Programming Language :: Python :: 3.11
Requires-Dist: pydantic (>=1.10.9,<2.0.0)
Requires-Dist: websockets (>=11.0,<12.0)
